plover_steno_engine_hooks_logger/__init__.py
plover_steno_engine_hooks_logger/extension.py
plover_steno_engine_hooks_logger/gui_tool.py
plover_steno_engine_hooks_logger/steno_engine_hooks/__init__.py
plover_steno_engine_hooks_logger/steno_engine_hooks/logger.py
plover_steno_engine_hooks_logger-0.3.6.dist-info/LICENSE.txt
plover_steno_engine_hooks_logger-0.3.6.dist-info/METADATA
plover_steno_engine_hooks_logger-0.3.6.dist-info/WHEEL
plover_steno_engine_hooks_logger-0.3.6.dist-info/entry_points.txt
plover_steno_engine_hooks_logger-0.3.6.dist-info/top_level.txt
plover_steno_engine_hooks_logger-0.3.6.dist-info/zip-safe
plover_steno_engine_hooks_logger-0.3.6.dist-info/RECORD
