Metadata-Version: 2.1
Name: plover-steno-engine-hooks-logger
Version: 0.3.6
Summary: Logs params given to Plover steno engine hooks
Home-page: https://github.com/paulfioravanti/plover-steno-engine-hooks-logger
Author: Paul Fioravanti
Author-email: paul@paulfioravanti.com
License: GNU General Public License v3 or later (GPLv3+)
Keywords: plover plover_plugin
Platform: UNKNOWN
Classifier: Development Status :: 4 - Beta
Classifier: Environment :: Plugins
Classifier: Intended Audience :: End Users/Desktop
Classifier: License :: OSI Approved :: GNU General Public License v3 or later (GPLv3+)
Classifier: Operating System :: OS Independent
Classifier: Programming Language :: Python :: 3
Classifier: Programming Language :: Python :: 3.9
License-File: LICENSE.txt
Requires-Dist: plover>=4.0.0rc2
Provides-Extra: test
Requires-Dist: mypy; extra == "test"
Requires-Dist: pylint; extra == "test"
